karellen/sqlite3/__init__.py
karellen/sqlite3/_sqlite.py
karellen/sqlite3/dbapi2.py
karellen_sqlite-0.0.3.dist-info/DESCRIPTION.rst
karellen_sqlite-0.0.3.dist-info/METADATA
karellen_sqlite-0.0.3.dist-info/RECORD
karellen_sqlite-0.0.3.dist-info/WHEEL
karellen_sqlite-0.0.3.dist-info/metadata.json
karellen_sqlite-0.0.3.dist-info/namespace_packages.txt
karellen_sqlite-0.0.3.dist-info/top_level.txt
karellen_sqlite-0.0.3.dist-info/zip-safe
pysqlite2/__init__.py
pysqlite2/dbapi2.py
