Metadata-Version: 2.0
Name: karellen-sqlite
Version: 0.0.3
Summary: Karellen Sqlite Extensions
Home-page: https://github.com/karellen/karellen-sqlite
Author: Karellen, Inc
Author-email: supervisor@karellen.co
License: Apache License, Version 2.0
Platform: UNKNOWN
Classifier: Development Status :: 5 - Production/Stable
Classifier: Environment :: Console
Classifier: Intended Audience :: Developers
Classifier: License :: OSI Approved :: Apache Software License
Classifier: Programming Language :: Python
Classifier: Programming Language :: Python :: 3.6
Classifier: Topic :: Database :: Database Engines/Servers
Classifier: Topic :: Software Development :: Libraries :: Python Modules
Obsoletes: pysqlite
